create_pipenv_project/__init__.py
create_pipenv_project/__main__.py
create_pipenv_project/py.typed
create_pipenv_project/terminal.py
create_pipenv_project/user_files/.gitignore
create_pipenv_project/user_files/__init__.py
create_pipenv_project/user_files/env
create_pipenv_project/user_files/environ.py
create_pipenv_project/user_files/logging.py
create_pipenv_project/user_files/mypy.ini
create_pipenv_project/user_files/run.py
create_pipenv_project/user_files/runners.py
create_pipenv_project-1.0.dist-info/METADATA
create_pipenv_project-1.0.dist-info/WHEEL
create_pipenv_project-1.0.dist-info/entry_points.txt
create_pipenv_project-1.0.dist-info/licenses/LICENSE
create_pipenv_project-1.0.dist-info/RECORD
