Metadata-Version: 2.4
Name: create_pipenv_project
Version: 1.0
Summary: A CLI tool for creating Python projects with Pipenv workflow.
Project-URL: Repository, https://github.com/nietsuu/create_pipenv_project
Author-email: Nie Tsuu <nietsuu@gmail.com>
License-File: LICENSE
Requires-Python: >=3.11
Requires-Dist: pipenv
